{
	"version": "7",
	"dialect": "sqlite",
	"entries": [
		{
			"idx": 0,
			"version": "6",
			"when": 1748818742198,
			"tag": "0000_short_wong",
			"breakpoints": true
		},
		{
			"idx": 1,
			"version": "6",
			"when": 1748827322259,
			"tag": "0001_omniscient_captain_universe",
			"breakpoints": true
		},
		{
			"idx": 2,
			"version": "6",
			"when": 1748837434871,
			"tag": "0002_chunky_silverclaw",
			"breakpoints": true
		},
		{
			"idx": 3,
			"version": "6",
			"when": 1748886756139,
			"tag": "0003_typical_ogun",
			"breakpoints": true
		},
		{
			"idx": 4,
			"version": "6",
			"when": 1748889342137,
			"tag": "0004_deep_meteorite",
			"breakpoints": true
		},
		{
			"idx": 5,
			"version": "6",
			"when": 1748988796406,
			"tag": "0005_aberrant_living_lightning",
			"breakpoints": true
		}
	]
}
